LICENSE.md
MANIFEST.in
README.md
setup.py
sermon/__init__.py
sermon/__main__.py
sermon/magics.py
sermon/resources.py
sermon/sermon.py
sermon/util.py
sermon.egg-info/PKG-INFO
sermon.egg-info/SOURCES.txt
sermon.egg-info/dependency_links.txt
sermon.egg-info/entry_points.txt
sermon.egg-info/requires.txt
sermon.egg-info/top_level.txt