Metadata-Version: 1.1
Name: sermon
Version: 1.0.1
Summary: Serial device monitor and transmitter.
Home-page: http://github.com/dbridges/sermon
Author: Daniel Bridges
Author-email: dan@dayofthenewdan.com
License: GPL3
Keywords: serial monitor console arduino
Platform: UNKNOWN
Classifier: License :: OSI Approved :: GNU General Public License v3 (GPLv3)
Classifier: Programming Language :: Python :: 2
Classifier: Programming Language :: Python :: 2.7
Classifier: Programming Language :: Python :: 3
Classifier: Programming Language :: Python :: 3.3
Classifier: Programming Language :: Python :: 3.4
Classifier: Topic :: Terminals :: Serial
